TurboImpute/__init__.py
TurboImpute/detection.py
TurboImpute/imputation.py
TurboImpute/removal.py
TurboImpute/visualization.py
tests/__init__.py
tests/test_detection.py
tests/test_imputation.py
tests/test_removal.py
tests/test_visualization.py
TurboImpute-0.1.0.dist-info/LICENSE
TurboImpute-0.1.0.dist-info/METADATA
TurboImpute-0.1.0.dist-info/WHEEL
TurboImpute-0.1.0.dist-info/top_level.txt
TurboImpute-0.1.0.dist-info/RECORD
