Metadata-Version: 2.1
Name: TurboImpute
Version: 0.1.0
Summary: A library for handling missing values in datasets
Home-page: https://github.com/valentinemwangi/TurboImpute
Author: Valentine Mwangi
Author-email: valentine@afterwork.ai
License: UNKNOWN
Platform: UNKNOWN
Classifier: Programming Language :: Python :: 3
Classifier: License :: OSI Approved :: MIT License
Classifier: Operating System :: OS Independent
Requires-Python: >=3.6
License-File: LICENSE
Requires-Dist: matplotlib
Requires-Dist: pandas
Requires-Dist: scikit-learn
Requires-Dist: seaborn
